async_gym_agents/agents/async_agent.py
async_gym_agents/agents/injector.py
async_gym_agents/agents/off_policy_injector.py
async_gym_agents/agents/on_policy_injector.py
async_gym_agents/envs/buggy_lunar_lander.py
async_gym_agents/envs/multi_env.py
async_gym_agents/envs/slow_cartpole.py
async_gym_agents/envs/threaded_env.py
async_gym_agents-0.1.6.dist-info/LICENCE
async_gym_agents-0.1.6.dist-info/METADATA
async_gym_agents-0.1.6.dist-info/WHEEL
async_gym_agents-0.1.6.dist-info/RECORD
