Metadata-Version: 2.3
Name: async-gym-agents
Version: 0.1.6
Summary: Async agents for Stable Baselines 3
License: Unlicense
Author: Jonas Peche
Author-email: jonas.peche@aon.at
Requires-Python: >=3.8
Classifier: License :: OSI Approved
Classifier: Programming Language :: Python :: 3
Classifier: Programming Language :: Python :: 3.8
Classifier: Programming Language :: Python :: 3.9
Classifier: Programming Language :: Python :: 3.10
Classifier: Programming Language :: Python :: 3.11
Classifier: Programming Language :: Python :: 3.12
Classifier: Programming Language :: Python :: 3.13
Requires-Dist: stable-baselines3[extra] (>=2.3.2,<3.0.0)
Requires-Dist: torchinfo (>=1.8.0,<2.0.0)
